{
    "general": {
        "stranumber": "1740047969848",
        "error_msg": [],
        "position": "SB",
        "initial_stack": 173.7,
        "about_hand": null,
        "detail_hand": null,
        "absent_count": 0,
        "table_stakes": "2_4_Flash",
        "each_player_id": {
            "CO": "anlz_000010",
            "BTN": "anlz_001340",
            "SB": "anlz_000696",
            "BB": "me",
            "UTG": "anlz_000410",
            "HJ": "anlz_000373"
        }
    },
    "preflop": {
        "general": {},
        "solutions": [
            {
                "pot": "1.5(pot/stack:1%(2%), gto:1.5)",
                "solution": {
                    "Allin100": 0.0,
                    "Raise3": 37.5,
                    "Call": 11.1,
                    "Fold": 51.5
                },
                "action": "Fold,(gto_near:Fold)",
                "situation": {
                    "all_Fold": {
                        "count": 4
                    }
                }
            }
        ]
    }
}